iracing_mcp/__init__.py
iracing_mcp/py.typed
iracing_mcp/entrypoints/__init__.py
iracing_mcp/entrypoints/server.py
iracing_mcp-0.1.1.dist-info/METADATA
iracing_mcp-0.1.1.dist-info/WHEEL
iracing_mcp-0.1.1.dist-info/entry_points.txt
iracing_mcp-0.1.1.dist-info/licenses/LICENSE
iracing_mcp-0.1.1.dist-info/RECORD
